python_qdairlines_helper-0.5.5.dist-info/licenses/LICENSE
qdairlines_helper/__init__.py
qdairlines_helper/config/__init__.py
qdairlines_helper/config/url_const.py
qdairlines_helper/controller/__init__.py
qdairlines_helper/controller/add_passenger.py
qdairlines_helper/controller/book_payment.py
qdairlines_helper/controller/book_search.py
qdairlines_helper/controller/cash_pax_info.py
qdairlines_helper/controller/home.py
qdairlines_helper/controller/nhlms_cashdesk.py
qdairlines_helper/controller/order_detail.py
qdairlines_helper/controller/order_query.py
qdairlines_helper/controller/order_verify.py
qdairlines_helper/controller/pay_success.py
qdairlines_helper/controller/user_login.py
qdairlines_helper/http/__init__.py
qdairlines_helper/http/flight_order.py
qdairlines_helper/http/http_base.py
qdairlines_helper/http/user_login.py
qdairlines_helper/po/__init__.py
qdairlines_helper/po/add_passenger_page.py
qdairlines_helper/po/air_order_page.py
qdairlines_helper/po/book_search_page.py
qdairlines_helper/po/cash_pax_info_page.py
qdairlines_helper/po/home_page.py
qdairlines_helper/po/login_page.py
qdairlines_helper/po/nhlms_cash_desk_page.py
qdairlines_helper/po/order_verify_page.py
qdairlines_helper/po/pay_success_page.py
qdairlines_helper/utils/__init__.py
qdairlines_helper/utils/po_utils.py
python_qdairlines_helper-0.5.5.dist-info/METADATA
python_qdairlines_helper-0.5.5.dist-info/WHEEL
python_qdairlines_helper-0.5.5.dist-info/top_level.txt
python_qdairlines_helper-0.5.5.dist-info/RECORD
