Metadata-Version: 2.4
Name: python_qdairlines_helper
Version: 0.5.5
Summary: qdairlines helper python package
Author-email: ckf10000 <ckf10000@sina.com>
License:                                  Apache License
Project-URL: Homepage, https://github.com/ckf10000/python-qdairlines-helper
Project-URL: Source, https://github.com/ckf10000/python-qdairlines-helper
Project-URL: Issues, https://github.com/ckf10000/python-qdairlines-helper/issues
Requires-Python: >=3.12
License-File: LICENSE
Requires-Dist: python_playwright_helper>=0.4.1
Requires-Dist: python_http_helper>=0.2.1
Requires-Dist: flight_helper>=0.3.3
Dynamic: license-file
